{
  "fetch_run_id": "ec624236-8c67-4fb0-a9f6-70744664ebe8",
  "source": "sleeper",
  "fetched_at": "2026-06-21T12:51:22.982833+00:00",
  "season": 2025,
  "week": null,
  "item_count": 25,
  "items": [
    {
      "sleeper_player_id": "13477",
      "resolved_player_id": "YOU154529",
      "player_name": "Colbie Young",
      "team": "CIN",
      "position": "WR",
      "news_body": "",
      "news_date": "2026-06-19T01:25:23.397000+00:00",
      "trending_count": 10332,
      "source": "sleeper"
    },
    {
      "sleeper_player_id": "13411",
      "resolved_player_id": "THO417520",
      "player_name": "Zavion Thomas",
      "team": "CHI",
      "position": "WR",
      "news_body": "",
      "news_date": "2026-05-02T14:10:49.496000+00:00",
      "trending_count": 3402,
      "source": "sleeper"
    },
    {
      "sleeper_player_id": "8800",
      "resolved_player_id": "00-0037563",
      "player_name": "Malik Davis",
      "team": "DAL",
      "position": "RB",
      "news_body": "",
      "news_date": "2026-06-03T22:05:59.513000+00:00",
      "trending_count": 3240,
      "source": "sleeper"
    },
    {
      "sleeper_player_id": "11592",
      "resolved_player_id": "00-0039814",
      "player_name": "Erick All",
      "team": "CIN",
      "position": "TE",
      "news_body": "",
      "news_date": "2026-06-11T23:20:47.729000+00:00",
      "trending_count": 3132,
      "source": "sleeper"
    },
    {
      "sleeper_player_id": "13306",
      "resolved_player_id": "GRE361852",
      "player_name": "Taylen Green",
      "team": "CLE",
      "position": "QB",
      "news_body": "",
      "news_date": "2026-06-19T13:40:11.978000+00:00",
      "trending_count": 2720,
      "source": "sleeper"
    },
    {
      "sleeper_player_id": "13296",
      "resolved_player_id": "DOU210628",
      "player_name": "Caleb Douglas",
      "team": "MIA",
      "position": "WR",
      "news_body": "",
      "news_date": "2026-06-04T20:30:35.782000+00:00",
      "trending_count": 2504,
      "source": "sleeper"
    },
    {
      "sleeper_player_id": "13424",
      "resolved_player_id": "MCG547540",
      "player_name": "Seth McGowan",
      "team": "IND",
      "position": "RB",
      "news_body": "",
      "news_date": "2026-06-18T13:40:16.014000+00:00",
      "trending_count": 2184,
      "source": "sleeper"
    },
    {
      "sleeper_player_id": "13413",
      "resolved_player_id": "ALL092954",
      "player_name": "Cyrus Allen",
      "team": "KC",
      "position": "WR",
      "news_body": "",
      "news_date": "2026-04-29T22:20:18.303000+00:00",
      "trending_count": 2100,
      "source": "sleeper"
    },
    {
      "sleeper_player_id": "8180",
      "resolved_player_id": "00-0037291",
      "player_name": "Jalen Nailor",
      "team": "LV",
      "position": "WR",
      "news_body": "",
      "news_date": "2026-06-16T13:20:21.691000+00:00",
      "trending_count": 1998,
      "source": "sleeper"
    },
    {
      "sleeper_player_id": "13324",
      "resolved_player_id": null,
      "player_name": "Matt Hibner",
      "team": "BAL",
      "position": "TE",
      "news_body": "",
      "news_date": "2026-05-02T19:15:51.743000+00:00",
      "trending_count": 1806,
      "source": "sleeper"
    },
    {
      "sleeper_player_id": "13348",
      "resolved_player_id": "TAY388181",
      "player_name": "J'Mari Taylor",
      "team": "JAX",
      "position": "RB",
      "news_body": "",
      "news_date": "2026-06-19T01:35:23.278000+00:00",
      "trending_count": 1701,
      "source": "sleeper"
    },
    {
      "sleeper_player_id": "8161",
      "resolved_player_id": "00-0038128",
      "player_name": "Malik Willis",
      "team": "MIA",
      "position": "QB",
      "news_body": "",
      "news_date": "2026-06-09T18:10:39.190000+00:00",
      "trending_count": 1659,
      "source": "sleeper"
    },
    {
      "sleeper_player_id": "13403",
      "resolved_player_id": "MIL303300",
      "player_name": "Jam Miller",
      "team": "NE",
      "position": "RB",
      "news_body": "",
      "news_date": "2026-06-19T01:55:23.574000+00:00",
      "trending_count": 1593,
      "source": "sleeper"
    },
    {
      "sleeper_player_id": "11783",
      "resolved_player_id": "00-0039410",
      "player_name": "Ryan Flournoy",
      "team": "DAL",
      "position": "WR",
      "news_body": "",
      "news_date": "2026-06-13T13:55:36.028000+00:00",
      "trending_count": 1480,
      "source": "sleeper"
    },
    {
      "sleeper_player_id": "2078",
      "resolved_player_id": "00-0031235",
      "player_name": "Odell Beckham",
      "team": "NYG",
      "position": "WR",
      "news_body": "",
      "news_date": "2026-06-01T17:50:39.194000+00:00",
      "trending_count": 1302,
      "source": "sleeper"
    },
    {
      "sleeper_player_id": "13421",
      "resolved_player_id": "RAR148318",
      "player_name": "Eli Raridon",
      "team": "NE",
      "position": "TE",
      "news_body": "",
      "news_date": "2026-05-02T19:30:51.843000+00:00",
      "trending_count": 1281,
      "source": "sleeper"
    },
    {
      "sleeper_player_id": "13335",
      "resolved_player_id": "PAY546690",
      "player_name": "Cole Payton",
      "team": "PHI",
      "position": "QB",
      "news_body": "",
      "news_date": "2026-06-19T14:00:12.357000+00:00",
      "trending_count": 1254,
      "source": "sleeper"
    },
    {
      "sleeper_player_id": "4017",
      "resolved_player_id": "00-0033537",
      "player_name": "Deshaun Watson",
      "team": "CLE",
      "position": "QB",
      "news_body": "",
      "news_date": "2026-06-18T21:25:23.942000+00:00",
      "trending_count": 1208,
      "source": "sleeper"
    },
    {
      "sleeper_player_id": "13319",
      "resolved_player_id": "DEL659316",
      "player_name": "Oscar Delp",
      "team": "NO",
      "position": "TE",
      "news_body": "",
      "news_date": "2026-06-18T07:45:15.975000+00:00",
      "trending_count": 1164,
      "source": "sleeper"
    },
    {
      "sleeper_player_id": "13408",
      "resolved_player_id": "KOZ404039",
      "player_name": "Tanner Koziol",
      "team": "JAX",
      "position": "TE",
      "news_body": "",
      "news_date": "2026-06-20T21:15:44.453000+00:00",
      "trending_count": 1104,
      "source": "sleeper"
    },
    {
      "sleeper_player_id": "13420",
      "resolved_player_id": "LAN016345",
      "player_name": "Bryce Lance",
      "team": "NO",
      "position": "WR",
      "news_body": "",
      "news_date": "2026-06-02T20:45:48.575000+00:00",
      "trending_count": 1050,
      "source": "sleeper"
    },
    {
      "sleeper_player_id": "13329",
      "resolved_player_id": "BEN601117",
      "player_name": "Malik Benson",
      "team": "LV",
      "position": "WR",
      "news_body": "",
      "news_date": "2026-05-01T04:35:29.970000+00:00",
      "trending_count": 1014,
      "source": "sleeper"
    },
    {
      "sleeper_player_id": "11625",
      "resolved_player_id": "00-0039890",
      "player_name": "Adonai Mitchell",
      "team": "NYJ",
      "position": "WR",
      "news_body": "",
      "news_date": "2026-06-04T02:35:01.291000+00:00",
      "trending_count": 1000,
      "source": "sleeper"
    },
    {
      "sleeper_player_id": "13303",
      "resolved_player_id": "KLU066027",
      "player_name": "Cade Klubnik",
      "team": "NYJ",
      "position": "QB",
      "news_body": "",
      "news_date": "2026-06-18T05:15:16.858000+00:00",
      "trending_count": 972,
      "source": "sleeper"
    },
    {
      "sleeper_player_id": "13414",
      "resolved_player_id": "BLA097235",
      "player_name": "Kaelon Black",
      "team": "SF",
      "position": "RB",
      "news_body": "",
      "news_date": "2026-05-14T04:20:30.218000+00:00",
      "trending_count": 959,
      "source": "sleeper"
    }
  ]
}